How2jJavaGaojiYingyongJiaochengFix1/README.md
How2jJavaGaojiYingyongJiaochengFix1/__init__.py
How2jJavaGaojiYingyongJiaochengFix1/__main__.py
How2jJavaGaojiYingyongJiaochengFix1/file.epub
How2jJavaGaojiYingyongJiaochengFix1/index.html
How2jJavaGaojiYingyongJiaochengFix1/css/__init__.py
How2jJavaGaojiYingyongJiaochengFix1/css/annotations.css
How2jJavaGaojiYingyongJiaochengFix1/css/main.css
How2jJavaGaojiYingyongJiaochengFix1/css/normalize.css
How2jJavaGaojiYingyongJiaochengFix1/css/popup.css
How2jJavaGaojiYingyongJiaochengFix1/font/__init__.py
How2jJavaGaojiYingyongJiaochengFix1/font/fontello.eot
How2jJavaGaojiYingyongJiaochengFix1/font/fontello.svg
How2jJavaGaojiYingyongJiaochengFix1/font/fontello.ttf
How2jJavaGaojiYingyongJiaochengFix1/font/fontello.woff
How2jJavaGaojiYingyongJiaochengFix1/img/__init__.py
How2jJavaGaojiYingyongJiaochengFix1/img/annotator-glyph-sprite.png
How2jJavaGaojiYingyongJiaochengFix1/img/annotator-icon-sprite.png
How2jJavaGaojiYingyongJiaochengFix1/img/apple-touch-icon.png
How2jJavaGaojiYingyongJiaochengFix1/img/cancelfullscreen.png
How2jJavaGaojiYingyongJiaochengFix1/img/close.png
How2jJavaGaojiYingyongJiaochengFix1/img/fullscreen.png
How2jJavaGaojiYingyongJiaochengFix1/img/loader.gif
How2jJavaGaojiYingyongJiaochengFix1/img/menu-icon.png
How2jJavaGaojiYingyongJiaochengFix1/img/save.png
How2jJavaGaojiYingyongJiaochengFix1/img/saved.png
How2jJavaGaojiYingyongJiaochengFix1/img/settings-s.png
How2jJavaGaojiYingyongJiaochengFix1/img/settings.png
How2jJavaGaojiYingyongJiaochengFix1/img/star.png
How2jJavaGaojiYingyongJiaochengFix1/js/__init__.py
How2jJavaGaojiYingyongJiaochengFix1/js/epub.js
How2jJavaGaojiYingyongJiaochengFix1/js/epub.min.js
How2jJavaGaojiYingyongJiaochengFix1/js/epub.min.map
How2jJavaGaojiYingyongJiaochengFix1/js/hooks.min.js
How2jJavaGaojiYingyongJiaochengFix1/js/hooks.min.map
How2jJavaGaojiYingyongJiaochengFix1/js/reader.js
How2jJavaGaojiYingyongJiaochengFix1/js/reader.js.map
How2jJavaGaojiYingyongJiaochengFix1/js/reader.min.js
how2j_java_gaoji_yingyong_jiaocheng_fix1-2025.3.25.0.dist-info/METADATA
how2j_java_gaoji_yingyong_jiaocheng_fix1-2025.3.25.0.dist-info/WHEEL
how2j_java_gaoji_yingyong_jiaocheng_fix1-2025.3.25.0.dist-info/entry_points.txt
how2j_java_gaoji_yingyong_jiaocheng_fix1-2025.3.25.0.dist-info/top_level.txt
how2j_java_gaoji_yingyong_jiaocheng_fix1-2025.3.25.0.dist-info/RECORD
